Metadata-Version: 1.0
Name: eecr-distributions
Version: 1.5
Summary: Gaussian and Binomial distributions
Home-page: UNKNOWN
Author: Ernesto Cornejo - Udacity course 2020
Author-email: ernestocornejo@hotmail.com
License: UNKNOWN
Platform: UNKNOWN
